uqoclient/Problem.py
uqoclient/Response.py
uqoclient/UQOExceptions.py
uqoclient/__init__.py
uqoclient/client/__init__.py
uqoclient/client/config.py
uqoclient/client/connection.py
uqoclient/examples/__init__.py
uqoclient/examples/examples.py
uqoclient/examples/graph_coloring_example.py
uqoclient/examples/util.py
uqoclient-1.0.3.dist-info/LICENSE
uqoclient-1.0.3.dist-info/METADATA
uqoclient-1.0.3.dist-info/WHEEL
uqoclient-1.0.3.dist-info/top_level.txt
uqoclient-1.0.3.dist-info/RECORD
