Metadata-Version: 2.1
Name: uqoclient
Version: 1.0.3
Summary: Client of the optimisation framework UQO
Home-page: https://github.com/pypa/sampleproject
Author: QAR-Lab Munich
Author-email: Sebastian.Zielinski@ifi.lmu.de
License: UNKNOWN
Platform: UNKNOWN
Classifier: Programming Language :: Python :: 3
Classifier: License :: OSI Approved :: MIT License
Classifier: Operating System :: OS Independent
Requires-Python: >=3.7
Requires-Dist: dimod (==0.9.10)
Requires-Dist: dwave-networkx (==0.8.8)
Requires-Dist: prettytable (==0.7.2)
Requires-Dist: pyzmq (==20.0.0)
Requires-Dist: matplotlib (==3.3.2)
